mycalc/calculator.py
axe_lee-0.0.1.dist-info/METADATA
axe_lee-0.0.1.dist-info/WHEEL
axe_lee-0.0.1.dist-info/top_level.txt
axe_lee-0.0.1.dist-info/RECORD
